README.md
setup.cfg
setup.py
LeanSim.egg-info/PKG-INFO
LeanSim.egg-info/SOURCES.txt
LeanSim.egg-info/dependency_links.txt
LeanSim.egg-info/entry_points.txt
LeanSim.egg-info/top_level.txt
leansim/__init__.py
leansim/main.py
leansim/worker.py
leansim/workflow.py