Metadata-Version: 1.0
Name: LeanSim
Version: 0.1
Summary: A simple Lean production simulation, meant for exploring lean management concepts and sharing in a lecture setting.
Home-page: https://github.com/nickdelgrosso/LeanSim
Author: Nicholas A. Del Grosso
Author-email: delgrosso.nick@gmail.com
License: MIT
Platform: UNKNOWN
